square_mipalo/__init__.py
square_mipalo/square_digits.py
square_mipalo-0.0.2.dist-info/METADATA
square_mipalo-0.0.2.dist-info/WHEEL
square_mipalo-0.0.2.dist-info/licenses/LICENSE
square_mipalo-0.0.2.dist-info/RECORD
