Metadata-Version: 2.1
Name: square_mipalo
Version: 0.0.2
Summary: Example package for university course
Author-email: Mihkel Paloots <mipalo@ttu.ee>
License-File: LICENSE
Classifier: License :: OSI Approved :: MIT License
Classifier: Operating System :: OS Independent
Classifier: Programming Language :: Python :: 3
Requires-Python: >=3.7
